Metadata-Version: 2.1
Name: analiz
Version: 1.0
Summary: Bu readme.md dosyasıdır.
Home-page: http://asadasd.com
Author: ilker yolunda gerek
Author-email: a@a.net
License: afl-3.0
Download-URL: https://www.ilkeryolundagerek.com
Keywords: Key1,Key2,Key3
Platform: UNKNOWN
License-File: LICENSE.txt
